SQobfuscator/__init__.py
SQobfuscator/module.py
sqobfuscate-0.1.dist-info/LICENSE
sqobfuscate-0.1.dist-info/METADATA
sqobfuscate-0.1.dist-info/WHEEL
sqobfuscate-0.1.dist-info/top_level.txt
sqobfuscate-0.1.dist-info/RECORD
