Metadata-Version: 2.2
Name: SQobfuscate
Version: 0.1
Summary: SQobfuscate Python Module One Step Ahead
Home-page: https://github.com/SyloraQ/SyloraQ
Author: SyloraQ
Author-email: syloraq.official@gmail.com
License: Proprietary
Classifier: Programming Language :: Python :: 3
Classifier: Intended Audience :: Developers
License-File: LICENSE
Dynamic: author
Dynamic: author-email
Dynamic: classifier
Dynamic: description
Dynamic: description-content-type
Dynamic: home-page
Dynamic: license
Dynamic: summary
